Metadata-Version: 1.0
Name: oaas-registry-api
Version: 1.0.1
Summary: oaas_registry_api
Home-page: UNKNOWN
Author: Bogdan Mustiata
Author-email: bogdan.mustiata@gmail.com
License: BSD
Platform: UNKNOWN
